venv_manager/__init__.py
venv_manager/main.py
venv_manager-0.0.1.dist-info/LICENSE
venv_manager-0.0.1.dist-info/METADATA
venv_manager-0.0.1.dist-info/WHEEL
venv_manager-0.0.1.dist-info/top_level.txt
venv_manager-0.0.1.dist-info/RECORD
