Metadata-Version: 2.1
Name: venv_manager
Version: 0.0.1
Summary: A Virtual Environment Manager
Author: Shrirang Mahajan
Author-email: shrirangmahajan123@gmail.com
Classifier: Programming Language :: Python :: 3
Classifier: License :: OSI Approved :: MIT License
Classifier: Operating System :: OS Independent
Requires-Python: >=3.8
License-File: LICENSE
